zheng_mcp_gaodeweather_server/__init__.py
zheng_mcp_gaodeweather_server/server.py
zheng_mcp_gaodeweather_server-0.1.0.dist-info/METADATA
zheng_mcp_gaodeweather_server-0.1.0.dist-info/WHEEL
zheng_mcp_gaodeweather_server-0.1.0.dist-info/entry_points.txt
zheng_mcp_gaodeweather_server-0.1.0.dist-info/RECORD
