Metadata-Version: 2.4
Name: zheng-mcp-gaodeweather-server
Version: 0.1.0
Summary: Add your description here
Requires-Python: >=3.10
Requires-Dist: mcp[cli]>=1.8.1
